<annotation>
	<folder>pembroke</folder>
	<filename>n02113023_1342.jpg</filename>
	<path>C:/Users/alexs/OneDrive/Documents/GitHub/models/research/images/train/pembroke/n02113023_1342.jpg</path>
	<source>
		<database>Unknown</database>
	</source>
	<size>
		<width>375</width>
		<height>500</height>
		<depth>3</depth>
	</size>
	<segmented>0</segmented>
	<object>
		<name>pembroke</name>
		<pose>Unspecified</pose>
		<truncated>1</truncated>
		<difficult>0</difficult>
		<bndbox>
			<xmin>1</xmin>
			<ymin>49</ymin>
			<xmax>365</xmax>
			<ymax>434</ymax>
		</bndbox>
	</object>
</annotation>
