<annotation>
	<folder>staging</folder>
	<filename>IMG_5858.jpg</filename>
	<path>/Users/mbolaris/git/coin_detector/models/research/object_detection/coin_detector/images/staging/IMG_5858.jpg</path>
	<source>
		<database>Unknown</database>
	</source>
	<size>
		<width>1024</width>
		<height>1365</height>
		<depth>3</depth>
	</size>
	<segmented>0</segmented>
	<object>
		<name>penny-lincoln</name>
		<pose>Unspecified</pose>
		<truncated>0</truncated>
		<difficult>0</difficult>
		<bndbox>
			<xmin>156</xmin>
			<ymin>755</ymin>
			<xmax>319</xmax>
			<ymax>905</ymax>
		</bndbox>
	</object>
	<object>
		<name>penny-lincoln</name>
		<pose>Unspecified</pose>
		<truncated>0</truncated>
		<difficult>0</difficult>
		<bndbox>
			<xmin>401</xmin>
			<ymin>816</ymin>
			<xmax>556</xmax>
			<ymax>971</ymax>
		</bndbox>
	</object>
	<object>
		<name>penny-lincoln</name>
		<pose>Unspecified</pose>
		<truncated>0</truncated>
		<difficult>0</difficult>
		<bndbox>
			<xmin>186</xmin>
			<ymin>996</ymin>
			<xmax>349</xmax>
			<ymax>1166</ymax>
		</bndbox>
	</object>
	<object>
		<name>penny-lincoln</name>
		<pose>Unspecified</pose>
		<truncated>0</truncated>
		<difficult>0</difficult>
		<bndbox>
			<xmin>347</xmin>
			<ymin>1086</ymin>
			<xmax>510</xmax>
			<ymax>1253</ymax>
		</bndbox>
	</object>
	<object>
		<name>penny-lincoln</name>
		<pose>Unspecified</pose>
		<truncated>0</truncated>
		<difficult>0</difficult>
		<bndbox>
			<xmin>519</xmin>
			<ymin>1070</ymin>
			<xmax>682</xmax>
			<ymax>1233</ymax>
		</bndbox>
	</object>
	<object>
		<name>penny-shield</name>
		<pose>Unspecified</pose>
		<truncated>0</truncated>
		<difficult>0</difficult>
		<bndbox>
			<xmin>314</xmin>
			<ymin>449</ymin>
			<xmax>462</xmax>
			<ymax>594</ymax>
		</bndbox>
	</object>
	<object>
		<name>penny-shield</name>
		<pose>Unspecified</pose>
		<truncated>0</truncated>
		<difficult>0</difficult>
		<bndbox>
			<xmin>551</xmin>
			<ymin>386</ymin>
			<xmax>714</xmax>
			<ymax>540</ymax>
		</bndbox>
	</object>
	<object>
		<name>penny-shield</name>
		<pose>Unspecified</pose>
		<truncated>0</truncated>
		<difficult>0</difficult>
		<bndbox>
			<xmin>699</xmin>
			<ymin>618</ymin>
			<xmax>845</xmax>
			<ymax>775</ymax>
		</bndbox>
	</object>
	<object>
		<name>penny-shield</name>
		<pose>Unspecified</pose>
		<truncated>0</truncated>
		<difficult>0</difficult>
		<bndbox>
			<xmin>634</xmin>
			<ymin>833</ymin>
			<xmax>793</xmax>
			<ymax>997</ymax>
		</bndbox>
	</object>
	<object>
		<name>dime-roosevelt</name>
		<pose>Unspecified</pose>
		<truncated>0</truncated>
		<difficult>0</difficult>
		<bndbox>
			<xmin>388</xmin>
			<ymin>612</ymin>
			<xmax>538</xmax>
			<ymax>759</ymax>
		</bndbox>
	</object>
	<object>
		<name>penny-lincoln</name>
		<pose>Unspecified</pose>
		<truncated>0</truncated>
		<difficult>0</difficult>
		<bndbox>
			<xmin>105</xmin>
			<ymin>536</ymin>
			<xmax>258</xmax>
			<ymax>679</ymax>
		</bndbox>
	</object>
</annotation>
