<annotation>
	<folder>staging</folder>
	<filename>IMG_5850.jpg</filename>
	<path>/Users/mbolaris/git/coin_detector/models/research/object_detection/coin_detector/images/staging/IMG_5850.jpg</path>
	<source>
		<database>Unknown</database>
	</source>
	<size>
		<width>612</width>
		<height>816</height>
		<depth>3</depth>
	</size>
	<segmented>0</segmented>
	<object>
		<name>penny-wheat</name>
		<pose>Unspecified</pose>
		<truncated>0</truncated>
		<difficult>0</difficult>
		<bndbox>
			<xmin>239</xmin>
			<ymin>29</ymin>
			<xmax>320</xmax>
			<ymax>111</ymax>
		</bndbox>
	</object>
	<object>
		<name>dime-roosevelt</name>
		<pose>Unspecified</pose>
		<truncated>0</truncated>
		<difficult>0</difficult>
		<bndbox>
			<xmin>249</xmin>
			<ymin>167</ymin>
			<xmax>320</xmax>
			<ymax>248</ymax>
		</bndbox>
	</object>
	<object>
		<name>quarter-washington</name>
		<pose>Unspecified</pose>
		<truncated>0</truncated>
		<difficult>0</difficult>
		<bndbox>
			<xmin>258</xmin>
			<ymin>290</ymin>
			<xmax>364</xmax>
			<ymax>400</ymax>
		</bndbox>
	</object>
</annotation>
