<annotation>
	<folder>staging</folder>
	<filename>IMG_5867.jpg</filename>
	<path>/Users/mbolaris/git/coin_detector/models/research/object_detection/coin_detector/images/staging/IMG_5867.jpg</path>
	<source>
		<database>Unknown</database>
	</source>
	<size>
		<width>1024</width>
		<height>1365</height>
		<depth>3</depth>
	</size>
	<segmented>0</segmented>
	<object>
		<name>penny-wheat</name>
		<pose>Unspecified</pose>
		<truncated>0</truncated>
		<difficult>0</difficult>
		<bndbox>
			<xmin>677</xmin>
			<ymin>383</ymin>
			<xmax>832</xmax>
			<ymax>542</ymax>
		</bndbox>
	</object>
	<object>
		<name>penny-wheat</name>
		<pose>Unspecified</pose>
		<truncated>0</truncated>
		<difficult>0</difficult>
		<bndbox>
			<xmin>380</xmin>
			<ymin>457</ymin>
			<xmax>547</xmax>
			<ymax>633</ymax>
		</bndbox>
	</object>
	<object>
		<name>penny-wheat</name>
		<pose>Unspecified</pose>
		<truncated>0</truncated>
		<difficult>0</difficult>
		<bndbox>
			<xmin>525</xmin>
			<ymin>610</ymin>
			<xmax>682</xmax>
			<ymax>771</ymax>
		</bndbox>
	</object>
	<object>
		<name>penny-wheat</name>
		<pose>Unspecified</pose>
		<truncated>0</truncated>
		<difficult>0</difficult>
		<bndbox>
			<xmin>729</xmin>
			<ymin>753</ymin>
			<xmax>890</xmax>
			<ymax>916</ymax>
		</bndbox>
	</object>
	<object>
		<name>penny-wheat</name>
		<pose>Unspecified</pose>
		<truncated>0</truncated>
		<difficult>0</difficult>
		<bndbox>
			<xmin>366</xmin>
			<ymin>855</ymin>
			<xmax>540</xmax>
			<ymax>1033</ymax>
		</bndbox>
	</object>
	<object>
		<name>nickel-buffalo</name>
		<pose>Unspecified</pose>
		<truncated>0</truncated>
		<difficult>0</difficult>
		<bndbox>
			<xmin>556</xmin>
			<ymin>988</ymin>
			<xmax>742</xmax>
			<ymax>1184</ymax>
		</bndbox>
	</object>
	<object>
		<name>nickel-buffalo</name>
		<pose>Unspecified</pose>
		<truncated>0</truncated>
		<difficult>0</difficult>
		<bndbox>
			<xmin>156</xmin>
			<ymin>657</ymin>
			<xmax>356</xmax>
			<ymax>851</ymax>
		</bndbox>
	</object>
</annotation>
